pywhoisxmlapi.py
pywhoisxmlapi-2.1.7.data/scripts/whois.py
pywhoisxmlapi-2.1.7.dist-info/LICENSE
pywhoisxmlapi-2.1.7.dist-info/METADATA
pywhoisxmlapi-2.1.7.dist-info/WHEEL
pywhoisxmlapi-2.1.7.dist-info/top_level.txt
pywhoisxmlapi-2.1.7.dist-info/RECORD
