Metadata-Version: 2.1
Name: pywhoisxmlapi
Version: 2.1.7
Summary: A unofficial client for WhoisXMLAPI
Home-page: https://seanthegeek.github.io/pywhoisxmlapi/
Author: Sean Whalen
Author-email: whalenster@gmail.com
License: Apache 2.0
Keywords: WHOIS,WWhoisXMLAPI
Platform: UNKNOWN
Classifier: Development Status :: 5 - Production/Stable
Classifier: Intended Audience :: Developers
Classifier: Intended Audience :: Information Technology
Classifier: Intended Audience :: Legal Industry
Classifier: Operating System :: OS Independent
Classifier: License :: OSI Approved :: Apache Software License
Classifier: Programming Language :: Python :: 2
Classifier: Programming Language :: Python :: 2.7
Classifier: Programming Language :: Python :: 3
Classifier: Programming Language :: Python :: 3.3
Classifier: Programming Language :: Python :: 3.4
Classifier: Programming Language :: Python :: 3.5
Classifier: Programming Language :: Python :: 3.6
Requires-Dist: requests
Requires-Dist: docopt
Requires-Dist: jsonplus
